{"name": "2.0.1 - BK7231N", "sub_name": "kltwfb_single_winctrl_rf_lns00", "type": "CLASSIC", "icon": "memory", "firmware": {"chip": "BK7231N", "name": "kltwfb_single_winctrl_rf_lns00", "version": "2.0.1", "sdk": "2.3.3-40.00"}, "data": {"address_finish": "0x1BD1B", "address_ssid": "0xBA94D", "address_ssid_padding": 4}, "slug": "kltwfb-single-winctrl-rf-lns00-2.0.1-sdk-2.3.3-40.00", "devices": [{"slug": "tuya-generic-qs-wifi-s10-c04-curtain-module-v2.0.1", "manufacturer": "Tuya Generic", "name": "QS-WIFI-S10-C04 Curtain Module v2.0.1", "image_url": "https://tuya-cloudcutter.github.io/images/thumbs/tuya-generic-qs-wifi-s10-c04-curtain-module-v2.0.1.jpg"}], "github_issues": [684]}