{"name": "1.1.5 - BK7231N", "sub_name": "oem_bk7231n_control_switch", "type": "CLASSIC", "icon": "toggle-switch-outline", "firmware": {"chip": "BK7231N", "name": "oem_bk7231n_control_switch", "version": "1.1.5", "sdk": "2.3.3-40.00", "key": "keyjnuy4s3kre7m7"}, "data": {"address_finish": "0x1B59B", "address_ssid": "0xC4205"}, "slug": "oem-bk7231n-control-switch-1.1.5-sdk-2.3.3-40.00", "devices": [{"slug": "tuya-generic-1ch-relay-with-rf", "manufacturer": "Tuya Generic", "name": "1CH Relay With RF", "image_url": "https://tuya-cloudcutter.github.io/images/thumbs/tuya-generic-1ch-relay-with-rf.jpg"}], "github_issues": [243]}