{"name": "1.0.12 - BK7231N", "sub_name": "ua_app", "type": "CLASSIC", "icon": "memory", "firmware": {"chip": "BK7231N", "name": "ua_app", "version": "1.0.12", "sdk": "2.3.3-40.00"}, "data": {"address_finish": "0x1B59B", "address_ssid": "0xBD9BD", "address_ssid_padding": 4}, "slug": "ua-app-1.0.12-sdk-2.3.3-40.00", "devices": [{"slug": "tuya-generic-swp86-01og-energy-monitoring-plug-v1.0.12", "manufacturer": "Tuya Generic", "name": "SWP86-01OG Energy Monitoring Plug v1.0.12", "image_url": "https://tuya-cloudcutter.github.io/images/thumbs/tuya-generic-swp86-01og-energy-monitoring-plug-v1.0.12.jpg"}, {"slug": "avatto-n-wot10-eu-plug-v1.0.12", "manufacturer": "Avatto", "name": "N-WOT10-EU Plug v1.0.12", "image_url": "https://tuya-cloudcutter.github.io/images/thumbs/avatto-n-wot10-eu-plug-v1.0.12.jpg"}], "github_issues": [393]}