{"name": "1.0.7 - OTA2 - RTL8710BN", "sub_name": "XYX_PRODUCT_KEY_DATA_KEY", "type": "CLASSIC", "icon": "memory", "firmware": {"chip": "RTL8710BN", "name": "XYX_PRODUCT_KEY_DATA_KEY", "version": "1.0.7", "sdk": "1.0.7-40.00", "key": "keymenctfd4sd3yq", "ota": "OTA2"}, "data": {"address_finish": "0x80FD443", "address_token": "0x80F4A9D"}, "slug": "xyx-product-key-data-key-ota2-1.0.7-sdk-ota2-1.0.7-40.00", "devices": [{"slug": "tuya-generic-lxu405-rgb-light-strip-ota2-v1.0.7", "manufacturer": "Tuya Generic", "name": "LXU405 RGB Light Strip ota1 v1.0.7"}], "github_issues": []}